ofold/__init__.py
ofold/utils.py
ofold-0.0.2.dist-info/AUTHORS.rst
ofold-0.0.2.dist-info/LICENSE.txt
ofold-0.0.2.dist-info/METADATA
ofold-0.0.2.dist-info/WHEEL
ofold-0.0.2.dist-info/top_level.txt
ofold-0.0.2.dist-info/RECORD
