Metadata-Version: 2.1
Name: ofold
Version: 0.0.2
Summary: Add a short description here!
Home-page: https://github.com/pyscaffold/pyscaffold/
Author: Vytautas Jancauskas
Author-email: unaudio@gmail.com
License: mit
Project-URL: Documentation, https://pyscaffold.org/
Platform: any
Classifier: Development Status :: 4 - Beta
Classifier: Programming Language :: Python
Requires-Dist: MIDIUtil (==1.2.1)
Provides-Extra: testing
Requires-Dist: pytest ; extra == 'testing'
Requires-Dist: pytest-cov ; extra == 'testing'
